{"name":"build-javascript","namedChunkGroups":{"app":{"name":"app","assets":[{"name":"webpack-runtime-3fb1ae1b3c32aaac6c53.js","size":4102},{"name":"styles.8e1dc577e9b55d400fa3.css","size":43944},{"name":"framework-0ac8b99dc88bf9fb1d3c.js","size":210279},{"name":"app-bcdda82fce5f91969655.js","size":67198}],"filteredAssets":0,"assetsSize":325523,"filteredAuxiliaryAssets":16,"auxiliaryAssetsSize":1016892},"component---src-pages-404-js":{"name":"component---src-pages-404-js","assets":[{"name":"styles.8e1dc577e9b55d400fa3.css","size":43944},{"name":"commons-44727970dc77ff0988b4.js","size":17791},{"name":"component---src-pages-404-js-7f9a9089d3886b9159b1.js","size":2203}],"filteredAssets":0,"assetsSize":63938,"filteredAuxiliaryAssets":15,"auxiliaryAssetsSize":353607},"component---src-pages-about-js":{"name":"component---src-pages-about-js","assets":[{"name":"styles.8e1dc577e9b55d400fa3.css","size":43944},{"name":"commons-44727970dc77ff0988b4.js","size":17791},{"name":"d4ad233efeb1d959420253442063e6db7488fdeb-a69253e6ed1fa7c78f04.js","size":8691},{"name":"component---src-pages-about-js-aea0a77aef08de213e64.js","size":1443}],"filteredAssets":0,"assetsSize":71869,"filteredAuxiliaryAssets":16,"auxiliaryAssetsSize":387684},"component---src-pages-index-js":{"name":"component---src-pages-index-js","assets":[{"name":"styles.8e1dc577e9b55d400fa3.css","size":43944},{"name":"commons-44727970dc77ff0988b4.js","size":17791},{"name":"d4ad233efeb1d959420253442063e6db7488fdeb-a69253e6ed1fa7c78f04.js","size":8691},{"name":"component---src-pages-index-js-b2031fa6ff41e464a8e1.js","size":621}],"filteredAssets":0,"assetsSize":71047,"filteredAuxiliaryAssets":16,"auxiliaryAssetsSize":386400},"component---src-pages-page-slug-js":{"name":"component---src-pages-page-slug-js","assets":[{"name":"styles.8e1dc577e9b55d400fa3.css","size":43944},{"name":"commons-44727970dc77ff0988b4.js","size":17791},{"name":"component---src-pages-page-slug-js-09dae87284e851dfb63f.js","size":1600}],"filteredAssets":0,"assetsSize":63335,"filteredAuxiliaryAssets":15,"auxiliaryAssetsSize":350557},"slice---src-components-footer-js":{"name":"slice---src-components-footer-js","assets":[{"name":"styles.8e1dc577e9b55d400fa3.css","size":43944},{"name":"commons-44727970dc77ff0988b4.js","size":17791},{"name":"slice---src-components-footer-js-3ef04dfbf3b428297292.js","size":17614}],"filteredAssets":0,"assetsSize":79349,"filteredAuxiliaryAssets":15,"auxiliaryAssetsSize":384137},"slice---src-components-header-js":{"name":"slice---src-components-header-js","assets":[{"name":"styles.8e1dc577e9b55d400fa3.css","size":43944},{"name":"commons-44727970dc77ff0988b4.js","size":17791},{"name":"slice---src-components-header-js-79dd5d4ab2f6e4aae10d.js","size":14762}],"filteredAssets":0,"assetsSize":76497,"filteredAuxiliaryAssets":15,"auxiliaryAssetsSize":391307}},"assetsByChunkName":{"app":["webpack-runtime-3fb1ae1b3c32aaac6c53.js","styles.8e1dc577e9b55d400fa3.css","framework-0ac8b99dc88bf9fb1d3c.js","app-bcdda82fce5f91969655.js"],"component---src-pages-404-js":["styles.8e1dc577e9b55d400fa3.css","commons-44727970dc77ff0988b4.js","component---src-pages-404-js-7f9a9089d3886b9159b1.js"],"component---src-pages-about-js":["styles.8e1dc577e9b55d400fa3.css","commons-44727970dc77ff0988b4.js","d4ad233efeb1d959420253442063e6db7488fdeb-a69253e6ed1fa7c78f04.js","component---src-pages-about-js-aea0a77aef08de213e64.js"],"component---src-pages-index-js":["styles.8e1dc577e9b55d400fa3.css","commons-44727970dc77ff0988b4.js","d4ad233efeb1d959420253442063e6db7488fdeb-a69253e6ed1fa7c78f04.js","component---src-pages-index-js-b2031fa6ff41e464a8e1.js"],"component---src-pages-page-slug-js":["styles.8e1dc577e9b55d400fa3.css","commons-44727970dc77ff0988b4.js","component---src-pages-page-slug-js-09dae87284e851dfb63f.js"],"slice---src-components-footer-js":["styles.8e1dc577e9b55d400fa3.css","commons-44727970dc77ff0988b4.js","slice---src-components-footer-js-3ef04dfbf3b428297292.js"],"slice---src-components-header-js":["styles.8e1dc577e9b55d400fa3.css","commons-44727970dc77ff0988b4.js","slice---src-components-header-js-79dd5d4ab2f6e4aae10d.js"]},"childAssetsByChunkName":{}}